LICENSE
README.md
fastapi_cache/__init__.py
fastapi_cache/backends/__init__.py
fastapi_cache/backends/dynamodb.py
fastapi_cache/backends/inmemory.py
fastapi_cache/backends/memcached.py
fastapi_cache/backends/redis.py
fastapi_cache/coder.py
fastapi_cache/decorator.py
fastapi_cache/key_builder.py
fastapi_cache/py.typed
fastapi_cache/types.py
fastapi_cache_ava-0.2.2.dist-info/LICENSE
fastapi_cache_ava-0.2.2.dist-info/METADATA
fastapi_cache_ava-0.2.2.dist-info/WHEEL
fastapi_cache_ava-0.2.2.dist-info/RECORD
