Metadata-Version: 2.1
Name: fastapi-cache-ava
Version: 0.2.2
Summary: Cache for FastAPI
Home-page: https://github.com/long2ice/fastapi-cache
License: Apache-2.0
Keywords: fastapi,cache,caching
Author: long2ice
Author-email: long2ice@gmail.com
Requires-Python: >=3.11,<4.0
Classifier: License :: OSI Approved :: Apache Software License
Classifier: Programming Language :: Python :: 3
Classifier: Programming Language :: Python :: 3.11
Classifier: Programming Language :: Python :: 3.12
Provides-Extra: all
Provides-Extra: dynamodb
Provides-Extra: memcache
Provides-Extra: redis
Requires-Dist: aiobotocore (>=1.4.1,<3.0.0) ; extra == "dynamodb" or extra == "all"
Requires-Dist: aiomcache ; extra == "memcache" or extra == "all"
Requires-Dist: fastapi
Requires-Dist: importlib-metadata (>=6.6.0,<7.0.0) ; python_version < "3.8"
Requires-Dist: pendulum
Requires-Dist: redis (>=4.2.0rc1,<5.0.0) ; extra == "redis" or extra == "all"
Requires-Dist: typing-extensions (>=4.12.2)
Requires-Dist: uvicorn
Project-URL: Documentation, https://github.com/long2ice/fastapi-cache
Project-URL: Repository, https://github.com/long2ice/fastapi-cache.git
